vitrea_host/__init__.py
vitrea_host/vbox_connection.py
vitrea_host/vbox_controller.py
vitrea_host/control_api/__init__.py
vitrea_host/control_api/commands/__init__.py
vitrea_host/control_api/commands/base.py
vitrea_host/control_api/commands/blind.py
vitrea_host/control_api/commands/connection.py
vitrea_host/control_api/commands/dimmer.py
vitrea_host/control_api/commands/dnd.py
vitrea_host/control_api/commands/fan.py
vitrea_host/control_api/commands/get_status.py
vitrea_host/control_api/commands/led_indicator.py
vitrea_host/control_api/commands/output.py
vitrea_host/control_api/commands/scenario.py
vitrea_host/control_api/commands/thermostat.py
vitrea_host/control_api/commands/toggle.py
vitrea_host/control_api/responses/__init__.py
vitrea_host/control_api/responses/vbox_responses.py
vitrea_host/control_api/responses/parsers/__init__.py
vitrea_host/control_api/responses/parsers/ac_status_response_parser.py
vitrea_host/control_api/responses/parsers/ack_response_parser.py
vitrea_host/control_api/responses/parsers/base.py
vitrea_host/control_api/responses/parsers/controller_clock_response_parser.py
vitrea_host/control_api/responses/parsers/error_response_parser.py
vitrea_host/control_api/responses/parsers/input_status_response_parser.py
vitrea_host/control_api/responses/parsers/output_status_response_parser.py
vitrea_host/control_api/responses/parsers/parser_factory.py
vitrea_host/control_api/responses/parsers/room_occupancy_response_parser.py
vitrea_host/control_api/responses/parsers/scenario_status_response_parser.py
vitrea_host/control_api/responses/parsers/status_response_parser.py
vitrea_host/control_api/responses/parsers/version_response_parser.py
vitrea_host/models/__init__.py
vitrea_host/models/base.py
vitrea_host/models/blind.py
vitrea_host/models/database.py
vitrea_host/models/dnd.py
vitrea_host/models/light.py
vitrea_host/models/push_button.py
vitrea_host/models/satellite.py
vitrea_host/models/scenario.py
vitrea_host/models/thermostat.py
vitrea_host-0.2.3.dist-info/licenses/LICENSE
vitrea_host-0.2.3.dist-info/METADATA
vitrea_host-0.2.3.dist-info/WHEEL
vitrea_host-0.2.3.dist-info/top_level.txt
vitrea_host-0.2.3.dist-info/RECORD
