Metadata-Version: 2.4
Name: vitrea-host
Version: 0.2.3
Summary: Python library for controlling Vitrea Smart Home Controllers via TCP
Author-email: Noam Aybes <noama@vitrea-sh.com>
License: Apache-2.0
Project-URL: Homepage, https://vitrea-sh.com
Project-URL: Documentation, https://github.com/vitrea-sh/py-vitrea-host
Project-URL: Repository, https://github.com/vitrea-sh/py-vitrea-host
Project-URL: Issues, https://github.com/vitrea-sh/py-vitrea-host/issues
Keywords: vitrea,smart-home,home-automation,iot
Classifier: Development Status :: 4 - Beta
Classifier: Intended Audience :: Developers
Classifier: License :: OSI Approved :: Apache Software License
Classifier: Operating System :: OS Independent
Classifier: Programming Language :: Python :: 3
Classifier: Programming Language :: Python :: 3.8
Classifier: Programming Language :: Python :: 3.9
Classifier: Programming Language :: Python :: 3.10
Classifier: Programming Language :: Python :: 3.11
Classifier: Programming Language :: Python :: 3.12
Classifier: Topic :: Home Automation
Classifier: Topic :: Software Development :: Libraries :: Python Modules
Requires-Python: >=3.8
License-File: LICENSE
Dynamic: license-file
